scipy_events/__init__.py
scipy_events/_core.py
scipy_events/change.py
scipy_events/progress.py
scipy_events/py.typed
scipy_events/steady_state.py
scipy_events/typing.py
scipy_events/tests/test_change.py
scipy_events/tests/test_issues.py
scipy_events/tests/test_params.py
scipy_events/tests/test_progress.py
scipy_events/tests/test_steady_state.py
scipy_events/tests/test_t_eval.py
scipy_events-0.4.4.dist-info/METADATA
scipy_events-0.4.4.dist-info/WHEEL
scipy_events-0.4.4.dist-info/RECORD
