Metadata-Version: 2.4
Name: scipy-events
Version: 0.4.4
Summary: A library of events for scipy.integrate.solve_ivp.
Project-URL: homepage, https://github.com/maurosilber/scipy-events
Project-URL: issues, https://github.com/maurosilber/scipy-events/issues
Project-URL: changelog, https://github.com/maurosilber/scipy-events/blob/main/CHANGELOG.md
Project-URL: documentation, https://maurosilber.github.io/scipy-events
Author-email: Mauro Silberberg <maurosilber@gmail.com>
License-Expression: MIT
Classifier: Programming Language :: Python :: 3
Requires-Python: >=3.10
Requires-Dist: numpy
Requires-Dist: scipy
